panel_sketch/__init__.py
panel_sketch/bokeh.ext.json
panel_sketch/config.py
panel_sketch/index.ts
panel_sketch/package-lock.json
panel_sketch/package.json
panel_sketch/sketch.py
panel_sketch/sketch_base.py
panel_sketch/sketch_editor.py
panel_sketch/sketch_viewer.py
panel_sketch/tsconfig.json
panel_sketch/dist/panel_sketch.js
panel_sketch/dist/panel_sketch.js.map
panel_sketch/dist/panel_sketch.json
panel_sketch/dist/panel_sketch.min.js
panel_sketch/dist/lib/index.d.ts
panel_sketch/dist/lib/index.js
panel_sketch/dist/lib/index.js.map
panel_sketch/dist/lib/models/index.d.ts
panel_sketch/dist/lib/models/index.js
panel_sketch/dist/lib/models/index.js.map
panel_sketch/dist/lib/models/sketch.d.ts
panel_sketch/dist/lib/models/sketch.js
panel_sketch/dist/lib/models/sketch.js.map
panel_sketch/models/__init__.py
panel_sketch/models/index.ts
panel_sketch/models/sketch.py
panel_sketch/models/sketch.ts
panel_sketch/sketch_compiler/__init__.py
panel_sketch/sketch_compiler/template_transcrypt_basic.py
panel_sketch/sketch_compiler/template_transcrypt_pyp5js.py
panel_sketch-20210411.2.dist-info/LICENSE
panel_sketch-20210411.2.dist-info/METADATA
panel_sketch-20210411.2.dist-info/WHEEL
panel_sketch-20210411.2.dist-info/top_level.txt
panel_sketch-20210411.2.dist-info/RECORD
