Metadata-Version: 2.1
Name: panel-sketch
Version: 20210411.2
Summary: To sketch high performing, interactive visualizations running in the browser
Home-page: https://github.com/MarcSkovMadsen/panel-sketch
Author: Marc Skov Madsen
Author-email: marc.skov.madsen@gmail.com
License: MIT
Platform: Windows
Platform: Mac OS X
Platform: Linux
Classifier: License :: OSI Approved :: MIT License
Classifier: Development Status :: 3 - Alpha
Classifier: Programming Language :: Python :: 3
Classifier: Programming Language :: Python :: 3.7
Classifier: Programming Language :: Python :: 3.8
Classifier: Programming Language :: Python :: 3.9
Classifier: Operating System :: OS Independent
Classifier: Intended Audience :: Developers
Classifier: Intended Audience :: Science/Research
Classifier: Intended Audience :: Financial and Insurance Industry
Classifier: Intended Audience :: Healthcare Industry
Classifier: Intended Audience :: Information Technology
Classifier: Intended Audience :: Legal Industry
Classifier: Intended Audience :: Other Audience
Classifier: Intended Audience :: Science/Research
Classifier: Natural Language :: English
Classifier: Topic :: Scientific/Engineering
Classifier: Topic :: Scientific/Engineering :: Visualization
Classifier: Topic :: Scientific/Engineering :: Information Analysis
Classifier: Topic :: Office/Business
Classifier: Topic :: Office/Business :: Financial
Classifier: Topic :: Software Development :: Libraries
Requires-Python: >=3.7
Requires-Dist: panel (>=0.11.1)
Requires-Dist: bokeh (>=2.3)
Provides-Extra: all
Requires-Dist: autoflake ; extra == 'all'
Requires-Dist: invoke ; extra == 'all'
Requires-Dist: isort ; extra == 'all'
Requires-Dist: jupyter-repo2docker ; extra == 'all'
Requires-Dist: jupyterlab ; extra == 'all'
Requires-Dist: mypy ; extra == 'all'
Requires-Dist: notebook ; extra == 'all'
Requires-Dist: pylint (>=2.6.0) ; extra == 'all'
Requires-Dist: pytest ; extra == 'all'
Requires-Dist: pytest-cov ; extra == 'all'
Requires-Dist: rope ; extra == 'all'
Requires-Dist: transcrypt ; extra == 'all'
Requires-Dist: twine ; extra == 'all'
Requires-Dist: wheel ; extra == 'all'
Provides-Extra: doc
Provides-Extra: examples
Requires-Dist: notebook ; extra == 'examples'
Requires-Dist: jupyterlab ; extra == 'examples'
Requires-Dist: transcrypt ; extra == 'examples'
Provides-Extra: recommended
Provides-Extra: tests
Requires-Dist: autoflake ; extra == 'tests'
Requires-Dist: invoke ; extra == 'tests'
Requires-Dist: isort ; extra == 'tests'
Requires-Dist: jupyter-repo2docker ; extra == 'tests'
Requires-Dist: mypy ; extra == 'tests'
Requires-Dist: pylint (>=2.6.0) ; extra == 'tests'
Requires-Dist: pytest ; extra == 'tests'
Requires-Dist: pytest-cov ; extra == 'tests'
Requires-Dist: rope ; extra == 'tests'
Requires-Dist: twine ; extra == 'tests'
Requires-Dist: wheel ; extra == 'tests'
